squic/__init__.py
squic/squic.py
squic-1.0.4.dist-info/LICENSE
squic-1.0.4.dist-info/METADATA
squic-1.0.4.dist-info/WHEEL
squic-1.0.4.dist-info/top_level.txt
squic-1.0.4.dist-info/RECORD
