Metadata-Version: 2.1
Name: squic
Version: 1.0.4
Summary: SQUIC is a second-order, L1-regularized maximum likelihood method for performant large-scale sparse precision matrix estimation. This repository contains the source code for the Python interface of SQUIC.
Home-page: https://www.gitlab.ci.inf.usi.ch/SQUIC/python
Author: Aryan Eftekhari, Lisa Gaedke-Merzhaeuser, Dimosthenis Pasadakis, Matthias Bollhoefer, Simon Scheidegger, Olaf Schenk
License: UNKNOWN
Platform: UNKNOWN
Classifier: Programming Language :: Python :: 3
Classifier: Operating System :: POSIX :: Linux
Classifier: Operating System :: MacOS
Classifier: License :: OSI Approved :: GNU General Public License (GPL)
Requires-Python: >=3.6
License-File: LICENSE
Requires-Dist: numpy
Requires-Dist: scipy
